{"_type":"export","__export_format":4,"__export_date":"2020-08-05T01:20:59.536Z","__export_source":"insomnia.desktop.app:v2020.3.3","resources":[{"_id":"req_04dd307f888149968625a2244c4a2351","authentication":{},"body":{"mimeType":"application/json","text":"{\n\t\"name\": \"Thiago Roberto\",\n\t\"avatar\": \"https://pbs.twimg.com/profile_images/1286256431071735808/yVJbgJVZ_400x400.jpg\",\n\t\"whatsapp\": \"19992760122\",\n\t\"bio\": \"Olá\",\n\t\"subject\": \"Programação\",\n\t\"cost\": 80,\n\t\"schedule\": [\n\t\t{\n\t\t\t\"week_day\": 1,\n\t\t\t\"from\": \"8:00\",\n\t\t\t\"to\": \"12:00\"\n\t\t},\n\t\t{\n\t\t\t\"week_day\": 3,\n\t\t\t\"from\": \"10:00\",\n\t\t\t\"to\": \"18:00\"\n\t\t},\n\t\t{\n\t\t\t\"week_day\": 4,\n\t\t\t\"from\": \"8:00\",\n\t\t\t\"to\": \"12:00\"\n\t\t}\n\t]\n}"},"created":1596582830501,"description":"","headers":[{"id":"pair_94e0029809ab4af18b61d435fcd1b4b5","name":"Content-Type","value":"application/json"}],"isPrivate":false,"metaSortKey":-1596582830501,"method":"POST","modified":1596589673691,"name":"Create class","parameters":[],"parentId":"fld_0fdc7051ba6d4edb8c024a053e992440","settingDisableRenderRequestBody":false,"settingEncodeUrl":true,"settingFollowRedirects":"global","settingRebuildPath":true,"settingSendCookies":true,"settingStoreCookies":true,"url":"http://localhost:3333/classes","_type":"request"},{"_id":"fld_0fdc7051ba6d4edb8c024a053e992440","created":1596589671465,"description":"","environment":{},"environmentPropertyOrder":null,"metaSortKey":-1596589671465,"modified":1596589671465,"name":"Classes","parentId":"wrk_e6e07ed3025b46f2bcf9c242b122eb65","_type":"request_group"},{"_id":"wrk_e6e07ed3025b46f2bcf9c242b122eb65","created":1596582792006,"description":"","modified":1596582792006,"name":"nlw-proffy","parentId":null,"scope":null,"_type":"workspace"},{"_id":"req_6b670bd50eec4fa1a2580d2e27653436","authentication":{},"body":{},"created":1596588478379,"description":"","headers":[],"isPrivate":false,"metaSortKey":-1596582830451,"method":"GET","modified":1596590105641,"name":"List classes","parameters":[{"description":"","id":"pair_6c6f02079a7b4874a990e4c6a6d4ede3","name":"week_day","value":"1"},{"description":"","disabled":false,"id":"pair_fa54d89f22714e9d80f6de3c2c353402","name":"subject","value":"Programação"},{"description":"","id":"pair_257a177f8ede44d0a5cf6517724c6a78","name":"time","value":"8:00"}],"parentId":"fld_0fdc7051ba6d4edb8c024a053e992440","settingDisableRenderRequestBody":false,"settingEncodeUrl":true,"settingFollowRedirects":"global","settingRebuildPath":true,"settingSendCookies":true,"settingStoreCookies":true,"url":"http://localhost:3333/classes","_type":"request"},{"_id":"req_46ea48ed5a044155a4ef7b2e458ace13","authentication":{},"body":{"mimeType":"application/json","text":"{\n\t\"user_id\": 1\n}"},"created":1596589656081,"description":"","headers":[{"id":"pair_94e0029809ab4af18b61d435fcd1b4b5","name":"Content-Type","value":"application/json"}],"isPrivate":false,"metaSortKey":-1595201032469.5,"method":"POST","modified":1596589688362,"name":"Create connections","parameters":[],"parentId":"fld_c21c337033ad4fa1ac33820f956f6fd7","settingDisableRenderRequestBody":false,"settingEncodeUrl":true,"settingFollowRedirects":"global","settingRebuildPath":true,"settingSendCookies":true,"settingStoreCookies":true,"url":"http://localhost:3333/connections","_type":"request"},{"_id":"fld_c21c337033ad4fa1ac33820f956f6fd7","created":1596589664835,"description":"","environment":{},"environmentPropertyOrder":null,"metaSortKey":-1596589664835,"modified":1596589664835,"name":"Connections","parentId":"wrk_e6e07ed3025b46f2bcf9c242b122eb65","_type":"request_group"},{"_id":"req_5d19ec8bef2946f48896e5574ec4a66c","authentication":{},"body":{},"created":1596590286046,"description":"","headers":[],"isPrivate":false,"metaSortKey":-1593128335422.25,"method":"GET","modified":1596590290153,"name":"List total connections","parameters":[],"parentId":"fld_c21c337033ad4fa1ac33820f956f6fd7","settingDisableRenderRequestBody":false,"settingEncodeUrl":true,"settingFollowRedirects":"global","settingRebuildPath":true,"settingSendCookies":true,"settingStoreCookies":true,"url":"http://localhost:3333/connections","_type":"request"},{"_id":"env_275eb250f6a9fb8968de994d1f2536935ae3bb98","color":null,"created":1596582792269,"data":{},"dataPropertyOrder":null,"isPrivate":false,"metaSortKey":1596582792269,"modified":1596582792269,"name":"Base Environment","parentId":"wrk_e6e07ed3025b46f2bcf9c242b122eb65","_type":"environment"},{"_id":"jar_275eb250f6a9fb8968de994d1f2536935ae3bb98","cookies":[],"created":1596582792284,"modified":1596582792284,"name":"Default Jar","parentId":"wrk_e6e07ed3025b46f2bcf9c242b122eb65","_type":"cookie_jar"},{"_id":"spc_4e40fdfb5bd64bbb8d613a01ef1250b6","contentType":"yaml","contents":"","created":1596582792013,"fileName":"nlw-proffy","modified":1596582792013,"parentId":"wrk_e6e07ed3025b46f2bcf9c242b122eb65","_type":"api_spec"}]}